medusa_network/Clients.py
medusa_network/Exceptions.py
medusa_network/Router.py
medusa_network/TcpServer.py
medusa_network/UdpServer.py
medusa_network/Utils.py
medusa_network/__init__.py
medusa_network-0.0.3.dist-info/AUTHORS.rst
medusa_network-0.0.3.dist-info/METADATA
medusa_network-0.0.3.dist-info/WHEEL
medusa_network-0.0.3.dist-info/top_level.txt
medusa_network-0.0.3.dist-info/RECORD
