Metadata-Version: 2.1
Name: medusa-network
Version: 0.0.3
Summary: Medusa Network Library
Home-page: UNKNOWN
Author: Andrea Mucci
Author-email: andrea@breda.build
License: UNKNOWN
Keywords: medusa_network
Platform: UNKNOWN
Classifier: Development Status :: 2 - Pre-Alpha
Classifier: Intended Audience :: Developers
Classifier: Natural Language :: English
Classifier: Programming Language :: Python :: 3
Classifier: Programming Language :: Python :: 3.5
Classifier: Programming Language :: Python :: 3.6
Classifier: Programming Language :: Python :: 3.7
Classifier: Programming Language :: Python :: 3.8
Requires-Python: >=3.5
Requires-Dist: medusa-protocol
Requires-Dist: aiomisc
